{"assets/Profile.png":["assets/Profile.png"],"assets/icons/C_sharp.png":["assets/icons/C_sharp.png"],"assets/icons/C_sharpM.png":["assets/icons/C_sharpM.png"],"assets/icons/Firebase.png":["assets/icons/Firebase.png"],"assets/icons/FirebaseM.png":["assets/icons/FirebaseM.png"],"assets/icons/Flutter.png":["assets/icons/Flutter.png"],"assets/icons/FlutterM.png":["assets/icons/FlutterM.png"],"assets/icons/Git.png":["assets/icons/Git.png"],"assets/icons/GitM.png":["assets/icons/GitM.png"],"assets/icons/JS_html_css.png":["assets/icons/JS_html_css.png"],"assets/icons/JS_html_cssM.png":["assets/icons/JS_html_cssM.png"],"assets/icons/MySql.png":["assets/icons/MySql.png"],"assets/icons/MySqlM.png":["assets/icons/MySqlM.png"],"assets/icons/asp-net.png":["assets/icons/asp-net.png"],"assets/icons/asp-netM.png":["assets/icons/asp-netM.png"],"assets/icons/pro1.png":["assets/icons/pro1.png"],"packages/cupertino_icons/assets/CupertinoIcons.ttf":["packages/cupertino_icons/assets/CupertinoIcons.ttf"],"packages/material_design_icons_flutter/lib/fonts/materialdesignicons-webfont.ttf":["packages/material_design_icons_flutter/lib/fonts/materialdesignicons-webfont.ttf"]}